{
  "producers": [
    {
      "location": "Cambridgeshire",
      "notes": "Cambridgeshire ",
      "products": [
        {
          "category": "cider",
          "status_text": "",
          "notes": "",
          "id": "b8b62c0100ee94d5efc14a3fe96276f2c767d4fb",
          "allergens": {},
          "dispense": "cider tub",
          "style": "",
          "name": "Cider",
          "bar": "",
          "abv": "6.0"
        }
      ],
      "id": "e5cb99e93e3a3839e702691c45d6cc28ffcabf9e",
      "name": "Accumulation",
      "year_founded": ""
    },
    {
      "location": "Cambridgeshire",
      "notes": "Cambridgeshire ",
      "products": [
        {
          "category": "cider",
          "status_text": "",
          "notes": "",
          "id": "862cfbec06b84e9debfe270a83c958cd8b69164b",
          "allergens": {},
          "dispense": "cider tub",
          "style": "",
          "name": "Cider",
          "bar": "",
          "abv": "6.5"
        }
      ],
      "id": "c803fa77ee10b52cd3d73c6af89cab266d2515a2",
      "name": "All Mixed Up",
      "year_founded": ""
    },
    {
      "location": "Hertfordshire",
      "notes": "Hertfordshire ",
      "products": [
        {
          "category": "cider",
          "status_text": "",
          "notes": "",
          "id": "ae46f54463e402e22467f5b8bf2ec3993015418a",
          "allergens": {},
          "dispense": "cider tub",
          "style": "Sweet",
          "name": "F.T.J. Filthy Tramp Juice",
          "bar": "",
          "abv": "6.7"
        },
        {
          "category": "cider",
          "status_text": "",
          "notes": "",
          "id": "fbc819f17514a85ccf38c29336e2bfe32facd7d9",
          "allergens": {},
          "dispense": "cider tub",
          "style": "",
          "name": "Thirst Aid",
          "bar": "",
          "abv": "5.4"
        }
      ],
      "id": "6c0ac76ca9fe1af889558d11fd9a75e1fb9a0b86",
      "name": "Apple Cottage",
      "year_founded": ""
    },
    {
      "location": "Northamptonshire",
      "notes": "Northamptonshire ",
      "products": [
        {
          "category": "cider",
          "status_text": "",
          "notes": "",
          "id": "ddde5d7eb04d95fa85bc87c860e20f0cf487c7f7",
          "allergens": {},
          "dispense": "cider tub",
          "style": "",
          "name": "Original",
          "bar": "",
          "abv": "5.9"
        }
      ],
      "id": "8a736be78e231f1c7105e34e796aad4ca9cb877d",
      "name": "Bad Boy",
      "year_founded": ""
    },
    {
      "location": "Worcestershire",
      "notes": "Worcestershire ",
      "products": [
        {
          "category": "cider",
          "status_text": "",
          "notes": "Dry fermented and conditioned in freshly-emptied rum and whisky casks.",
          "id": "d84e76be655ef3508f9d307e0b7304affd237239",
          "allergens": {},
          "dispense": "cider tub",
          "style": "Dry",
          "name": "Oak Cask",
          "bar": "",
          "abv": "7.4"
        }
      ],
      "id": "ccd04939f25266ed88d9dbb3eb298866911b04f4",
      "name": "Barbourne",
      "year_founded": ""
    },
    {
      "location": "Cambridgeshire",
      "notes": "Cambridgeshire ",
      "products": [
        {
          "category": "cider",
          "status_text": "",
          "notes": "",
          "id": "cf9dc3bbca75cb990c30618e1c3391be52ccb934",
          "allergens": {},
          "dispense": "cider tub",
          "style": "",
          "name": "Hardcore",
          "bar": "",
          "abv": "7.0"
        },
        {
          "category": "cider",
          "status_text": "",
          "notes": "",
          "id": "b0744936fd312408135150d8a83b82b6912b52b7",
          "allergens": {},
          "dispense": "cider tub",
          "style": "",
          "name": "Smoking Barrels II (whiskey cask)",
          "bar": "",
          "abv": "7.4"
        },
        {
          "category": "cider",
          "status_text": "",
          "notes": "",
          "id": "7ccfd40fab67c345c2fbab20d9ac73abbe581e91",
          "allergens": {},
          "dispense": "cider tub",
          "style": "",
          "name": "Trees Are Good",
          "bar": "",
          "abv": "7.2"
        }
      ],
      "id": "66d5d06e4ffd42ac6765baafb597a3c6bc5b53c3",
      "name": "Blue Barrel",
      "year_founded": ""
    },
    {
      "location": "Norfolk",
      "notes": "Norfolk ",
      "products": [
        {
          "category": "cider",
          "status_text": "",
          "notes": "",
          "id": "2860a7ffe02c1f107b5f6f25660cdba5feed4e2c",
          "allergens": {},
          "dispense": "cider tub",
          "style": "",
          "name": "Monty's Double",
          "bar": "",
          "abv": "6.0"
        }
      ],
      "id": "cd8b7a4b8bb9bbf442a9d50fa465fe0e9d868a13",
      "name": "Burnard's",
      "year_founded": ""
    },
    {
      "location": "Somerset",
      "notes": "Somerset ",
      "products": [
        {
          "category": "cider",
          "status_text": "",
          "notes": "",
          "id": "41006fa99247594eb3eec2378c2cbe6087ceb8cb",
          "allergens": {},
          "dispense": "cider tub",
          "style": "",
          "name": "Cider",
          "bar": "",
          "abv": "6.0"
        }
      ],
      "id": "8b05af0ef2eac32530836bcebd512f38e0beae64",
      "name": "Burrow Hill",
      "year_founded": ""
    },
    {
      "location": "Cambridgeshire",
      "notes": "Cambridgeshire ",
      "products": [
        {
          "category": "cider",
          "status_text": "",
          "notes": "",
          "id": "275add43bf97bace4ecc2d68bfbaccaaace8f09f",
          "allergens": {},
          "dispense": "cider tub",
          "style": "Dry",
          "name": "Discovery (SV)",
          "bar": "",
          "abv": "7.3"
        },
        {
          "category": "cider",
          "status_text": "",
          "notes": "",
          "id": "c94ba48c5062f8139f652888c6db4c8cb56fdf70",
          "allergens": {},
          "dispense": "cider tub",
          "style": "",
          "name": "Kingston Black (SV)",
          "bar": "",
          "abv": "7.0"
        },
        {
          "category": "cider",
          "status_text": "",
          "notes": "",
          "id": "8b98aa855f28a42bc225004ed0e99a7068ae9c3e",
          "allergens": {},
          "dispense": "cider tub",
          "style": "",
          "name": "Saturn (SV)",
          "bar": "",
          "abv": "7.3"
        },
        {
          "category": "cider",
          "status_text": "",
          "notes": "",
          "id": "7f111b6b75ca0dc2c1c176bcd723107bd02536e7",
          "allergens": {},
          "dispense": "cider tub",
          "style": "Medium",
          "name": "Scrumptious (SV)",
          "bar": "",
          "abv": "7.7"
        }
      ],
      "id": "75988f5ac0575a8d3636291a136cf92664152ed3",
      "name": "Cam Valley Orchards",
      "year_founded": ""
    },
    {
      "location": "Cambridgeshire",
      "notes": "Cambridgeshire ",
      "products": [
        {
          "category": "cider",
          "status_text": "",
          "notes": "",
          "id": "a8a7c57675bfaaef6c33489b775985b7947470f1",
          "allergens": {},
          "dispense": "cider tub",
          "style": "Medium",
          "name": "Angry Wasp",
          "bar": "",
          "abv": "6.5"
        },
        {
          "category": "cider",
          "status_text": "",
          "notes": "",
          "id": "d6f1da8e8514c387f0194a406693503897787926",
          "allergens": {},
          "dispense": "cider tub",
          "style": "Sweet",
          "name": "Much Merriment",
          "bar": "",
          "abv": "6.5"
        },
        {
          "category": "cider",
          "status_text": "",
          "notes": "",
          "id": "893469d27c4b56cc215a847b7668b4674d4ca0c4",
          "allergens": {},
          "dispense": "cider tub",
          "style": "Medium dry",
          "name": "Scratter's Reward",
          "bar": "",
          "abv": "6.8"
        }
      ],
      "id": "6d1270b059e6137ec41ef691abd46e1c01a3a0f5",
      "name": "Cambridge Cider Co.",
      "year_founded": ""
    },
    {
      "location": "Cambridgeshire",
      "notes": "Cambridgeshire ",
      "products": [
        {
          "category": "cider",
          "status_text": "",
          "notes": "",
          "id": "5599cf2950af1cce42566d5fbc6ef66331a0960b",
          "allergens": {},
          "dispense": "cider tub",
          "style": "",
          "name": "Bish Bash Bosh",
          "bar": "",
          "abv": "6.0"
        },
        {
          "category": "cider",
          "status_text": "",
          "notes": "",
          "id": "ab7023e449bd22376037ef65dd4ba14d35e11246",
          "allergens": {},
          "dispense": "cider tub",
          "style": "",
          "name": "Luvvly Jubbly",
          "bar": "",
          "abv": "6.2"
        }
      ],
      "id": "3a5e5bbcbc3e4447b4d73925f03973c0294b95cc",
      "name": "Camrose",
      "year_founded": ""
    },
    {
      "location": "Herefordshire",
      "notes": "Herefordshire ",
      "products": [
        {
          "category": "cider",
          "status_text": "",
          "notes": "",
          "id": "27e01e60a1fe1e400752389846cc69ba6710cd75",
          "allergens": {},
          "dispense": "cider tub",
          "style": "Medium",
          "name": "Thundering Molly",
          "bar": "",
          "abv": "5.2"
        }
      ],
      "id": "28cc2209b234d9183848f1c6a8ff13e0311057b9",
      "name": "Celtic Marches",
      "year_founded": ""
    },
    {
      "location": "Cambridgeshire",
      "notes": "Cambridgeshire ",
      "products": [
        {
          "category": "cider",
          "status_text": "",
          "notes": "",
          "id": "42c161c5355a75b82fa535572db7b9b3dd28fc9b",
          "allergens": {},
          "dispense": "cider tub",
          "style": "",
          "name": "Cider",
          "bar": "",
          "abv": "6.0"
        }
      ],
      "id": "64bed117196c2624f38bb8da114684eeb96ff68a",
      "name": "Combination",
      "year_founded": ""
    },
    {
      "location": "Cambridgeshire",
      "notes": "Cambridgeshire ",
      "products": [
        {
          "category": "cider",
          "status_text": "",
          "notes": "",
          "id": "ab95cea89e221a681f6a22ff8556a376599bd841",
          "allergens": {},
          "dispense": "cider tub",
          "style": "",
          "name": "Premium Apple Cider",
          "bar": "",
          "abv": "4.8"
        },
        {
          "category": "cider",
          "status_text": "",
          "notes": "",
          "id": "6b28b4c108558abae77e73790992acf780147061",
          "allergens": {},
          "dispense": "bottle",
          "style": "",
          "name": "Premium Low Alcohol Cider",
          "bar": "",
          "abv": "0.5"
        }
      ],
      "id": "6169f508654f8eab558f04d4aa2dfa57c7034b75",
      "name": "Cranes",
      "year_founded": ""
    },
    {
      "location": "Cambridgeshire",
      "notes": "Cambridgeshire ",
      "products": [
        {
          "category": "cider",
          "status_text": "",
          "notes": "",
          "id": "c3780f1bf13c6a9506ae61d45f775ef2a2a515c4",
          "allergens": {
            "sulphites": true
          },
          "dispense": "cider tub",
          "style": "Medium",
          "name": "Oliver's Choice",
          "bar": "",
          "abv": "5.8"
        },
        {
          "category": "cider",
          "status_text": "",
          "notes": "",
          "id": "ea551b9d70a18414056b3b882ec42f77d16e7b11",
          "allergens": {},
          "dispense": "cider tub",
          "style": "",
          "name": "Oliver's Downfall (cask matured)",
          "bar": "",
          "abv": "6.7"
        },
        {
          "category": "cider",
          "status_text": "",
          "notes": "",
          "id": "b179ee2e682d90f5caaf4d80d10d4b878ab480cd",
          "allergens": {},
          "dispense": "cider tub",
          "style": "",
          "name": "Oliver's Last Gasp",
          "bar": "",
          "abv": "5.8"
        },
        {
          "category": "cider",
          "status_text": "",
          "notes": "",
          "id": "7a68829d273c11bcba0e80b70aedd9d39c8047c8",
          "allergens": {},
          "dispense": "cider tub",
          "style": "",
          "name": "Oliver's Session",
          "bar": "",
          "abv": "4.5"
        },
        {
          "category": "cider",
          "status_text": "",
          "notes": "",
          "id": "f346a479862d20b8bc65bd3f4109131bc565e109",
          "allergens": {
            "sulphites": true
          },
          "dispense": "cider tub",
          "style": "Medium sweet",
          "name": "Oliver's Sweetheart",
          "bar": "",
          "abv": "5.8"
        }
      ],
      "id": "5dd8b53aacfc461407333cffac2e4acce3337ebf",
      "name": "Cromwell",
      "year_founded": ""
    },
    {
      "location": "Norfolk",
      "notes": "Norfolk ",
      "products": [
        {
          "category": "cider",
          "status_text": "",
          "notes": "",
          "id": "178a44b0522cbcc4ff0515de81ae92cfe1baaf7f",
          "allergens": {},
          "dispense": "cider tub",
          "style": "",
          "name": "Special Reserve",
          "bar": "",
          "abv": "6.9"
        }
      ],
      "id": "e076fa133a86ed3f260850a0dc70993ae366a649",
      "name": "Crone's",
      "year_founded": ""
    },
    {
      "location": "Dorset",
      "notes": "Dorset ",
      "products": [
        {
          "category": "cider",
          "status_text": "",
          "notes": "Sweet and lighter version of a traditional farmhouse. Unpasteurised, no sulphite.",
          "id": "9ff6ce92cb5f1c73ba9ec5baf4b87ee7b5b1b9af",
          "allergens": {},
          "dispense": "cider tub",
          "style": "Sweet",
          "name": "Summer Sunshine",
          "bar": "",
          "abv": "5.0"
        }
      ],
      "id": "3c24f257fbe14b58141a0ab7dbd5484c1d561f2c",
      "name": "Dorset Sunshine",
      "year_founded": ""
    },
    {
      "location": "Norfolk",
      "notes": "Norfolk ",
      "products": [
        {
          "category": "cider",
          "status_text": "",
          "notes": "",
          "id": "5df9769ff6d2b5b8ebf5629d3f3b0ef1fe07f262",
          "allergens": {},
          "dispense": "cider tub",
          "style": "",
          "name": "BOB",
          "bar": "",
          "abv": "7.5"
        },
        {
          "category": "cider",
          "status_text": "",
          "notes": "",
          "id": "93f06adf20e3e449ba1183be20546d2d94ad334b",
          "allergens": {},
          "dispense": "cider tub",
          "style": "",
          "name": "Jonagold (SV)",
          "bar": "",
          "abv": "6.1"
        },
        {
          "category": "cider",
          "status_text": "",
          "notes": "",
          "id": "7503e43bc3ae307da6e6037c6188ebb308ce64b0",
          "allergens": {},
          "dispense": "cider tub",
          "style": "",
          "name": "Stray Horse",
          "bar": "",
          "abv": "5.8"
        }
      ],
      "id": "5a5f42d2a90c9103167e8ebb5dd94727134b1155",
      "name": "Downham",
      "year_founded": ""
    },
    {
      "location": "Cambridgeshire",
      "notes": "Cambridgeshire ",
      "products": [
        {
          "category": "cider",
          "status_text": "",
          "notes": "",
          "id": "cbc3a40aa0747a51f434eb068408b67b2b9e0d01",
          "allergens": {},
          "dispense": "cider tub",
          "style": "",
          "name": "Cidermonger ",
          "bar": "",
          "abv": "6.5"
        },
        {
          "category": "cider",
          "status_text": "",
          "notes": "",
          "id": "7c6647144660e7b0fc6e267cffa96b778daeb75e",
          "allergens": {},
          "dispense": "cider tub",
          "style": "",
          "name": "Direct Hit",
          "bar": "",
          "abv": "6.0"
        },
        {
          "category": "cider",
          "status_text": "",
          "notes": "",
          "id": "93267c6991a724f176a8deb7457d31ead9a73c63",
          "allergens": {},
          "dispense": "cider tub",
          "style": "",
          "name": "Russet (SV)",
          "bar": "",
          "abv": "8.5"
        },
        {
          "category": "cider",
          "status_text": "",
          "notes": "",
          "id": "8e46345895f178b627f80fdc3f18a99960c7e2fc",
          "allergens": {},
          "dispense": "cider tub",
          "style": "",
          "name": "Wisley Crab (SV)",
          "bar": "",
          "abv": "6.3"
        },
        {
          "category": "cider",
          "status_text": "",
          "notes": "",
          "id": "42c3544ac6e6b71cc0e8f9adc646bc58dfd41171",
          "allergens": {},
          "dispense": "cider tub",
          "style": "",
          "name": "Wormhole ",
          "bar": "",
          "abv": "6.8"
        }
      ],
      "id": "509f6ccbc5a85a0d07f32bff32186163ba8301b8",
      "name": "Duxford Scrumpy Co.",
      "year_founded": ""
    },
    {
      "location": "Norfolk",
      "notes": "Norfolk ",
      "products": [
        {
          "category": "cider",
          "status_text": "",
          "notes": "",
          "id": "4aa0a5fd949fc7c07763fe676b3bf3766282eddb",
          "allergens": {},
          "dispense": "cider tub",
          "style": "",
          "name": "Radiant Rose",
          "bar": "",
          "abv": "4.8"
        }
      ],
      "id": "ac9c957760424d463fbc0a28712e09dcd11a9415",
      "name": "East Norfolk",
      "year_founded": ""
    },
    {
      "location": "Cambridgeshire",
      "notes": "Cambridgeshire ",
      "products": [
        {
          "category": "cider",
          "status_text": "",
          "notes": "",
          "id": "cbfb0b5276414fb620dc35ef0122d178848221fe",
          "allergens": {},
          "dispense": "cider tub",
          "style": "Dry",
          "name": "Weasel's Wevenge",
          "bar": "",
          "abv": "6.8"
        }
      ],
      "id": "570722b44ec7003126d686b70703051e72ff7408",
      "name": "Ermine's Treat",
      "year_founded": ""
    },
    {
      "location": "Cambridgeshire",
      "notes": "Cambridgeshire ",
      "products": [
        {
          "category": "cider",
          "status_text": "",
          "notes": "",
          "id": "253d63be08dea0f9275da0cddc78e5defe99ce38",
          "allergens": {},
          "dispense": "bottle",
          "style": "",
          "name": "English Cider (2021 harvest)",
          "bar": "",
          "abv": "6.7"
        }
      ],
      "id": "49769d1b566ad14d8edfdb57d777fd3f6fe6e39a",
      "name": "Foxhay",
      "year_founded": ""
    },
    {
      "location": "Cambridgeshire",
      "notes": "Cambridgeshire est. 2003",
      "products": [
        {
          "category": "cider",
          "status_text": "",
          "notes": "",
          "id": "fb49a5eb0f4cb550a5e57b3c252292dc58876e37",
          "allergens": {},
          "dispense": "cider tub",
          "style": "Medium",
          "name": "Get Slaughtered",
          "bar": "",
          "abv": "8.0"
        }
      ],
      "id": "0a57cb53ba59c46fc4b692527a38a87c78d84028",
      "name": "Hereward",
      "year_founded": "2003"
    },
    {
      "location": "Cambridgeshire",
      "notes": "Cambridgeshire ",
      "products": [
        {
          "category": "cider",
          "status_text": "",
          "notes": "Cloudy.",
          "id": "846be064e055aaae670e92dc7f7362f3426f594a",
          "allergens": {},
          "dispense": "cider tub",
          "style": "Very sweet",
          "name": "'Ang Over",
          "bar": "",
          "abv": "8.5"
        },
        {
          "category": "cider",
          "status_text": "",
          "notes": "",
          "id": "b9d7a531ac3d912a60f6ec53824067164a356911",
          "allergens": {},
          "dispense": "cider tub",
          "style": "",
          "name": "'Ard Core",
          "bar": "",
          "abv": "7.0"
        }
      ],
      "id": "e194ee413805ba5a6aabf4d34db2066149dc0369",
      "name": "Hubz's",
      "year_founded": ""
    },
    {
      "location": "Kent",
      "notes": "Kent ",
      "products": [
        {
          "category": "cider",
          "status_text": "",
          "notes": "",
          "id": "1adf02784f355ec29558fe534a00dd1f8e065511",
          "allergens": {},
          "dispense": "cider tub",
          "style": "",
          "name": "Grafter",
          "bar": "",
          "abv": "6.2"
        }
      ],
      "id": "c2f228e7e2baf57a537893f20f0615908410ad15",
      "name": "Kentish Pip",
      "year_founded": ""
    },
    {
      "location": "Devon",
      "notes": "Devon ",
      "products": [
        {
          "category": "cider",
          "status_text": "",
          "notes": "",
          "id": "8dc255639e112df740133b7b4559735b7bef5d43",
          "allergens": {},
          "dispense": "cider tub",
          "style": "",
          "name": "Scrumpy",
          "bar": "",
          "abv": "6.0"
        }
      ],
      "id": "14019988a92023b21c8fbafb2b615c6ce575da38",
      "name": "Lyme Bay",
      "year_founded": ""
    },
    {
      "location": "Cambridgeshire",
      "notes": "Cambridgeshire ",
      "products": [
        {
          "category": "cider",
          "status_text": "",
          "notes": "",
          "id": "6b34db7470065597b75efd287ca752e006d6f1ef",
          "allergens": {},
          "dispense": "cider tub",
          "style": "",
          "name": "Cider",
          "bar": "",
          "abv": "7.0"
        }
      ],
      "id": "7e79a3af2634de6635e59c9404d251b3955d39f9",
      "name": "Mallus Aforethought",
      "year_founded": ""
    },
    {
      "location": "Essex",
      "notes": "Essex ",
      "products": [
        {
          "category": "cider",
          "status_text": "",
          "notes": "",
          "id": "6959db5800ba4f8057b25f7cecbfea47ae5e3451",
          "allergens": {},
          "dispense": "cider tub",
          "style": "",
          "name": "Cider",
          "bar": "",
          "abv": "6.0"
        }
      ],
      "id": "0fad831960c1f2e6f2b3c5e43c851e39141c50ca",
      "name": "Mill Lane",
      "year_founded": ""
    },
    {
      "location": "Cambridgeshire",
      "notes": "Cambridgeshire ",
      "products": [
        {
          "category": "cider",
          "status_text": "",
          "notes": "",
          "id": "7bda8c4212412587aba0f384c8986d622db7a803",
          "allergens": {},
          "dispense": "cider tub",
          "style": "",
          "name": "Cider",
          "bar": "",
          "abv": "6.5"
        }
      ],
      "id": "42271387fd9aeff9e75d653d2f08c7da3e3d8ec6",
      "name": "Miss Terry",
      "year_founded": ""
    },
    {
      "location": "Norfolk",
      "notes": "Norfolk ",
      "products": [
        {
          "category": "cider",
          "status_text": "",
          "notes": "",
          "id": "a5d5807e215c503b2801c55935e8f724f772d2ab",
          "allergens": {},
          "dispense": "cider tub",
          "style": "",
          "name": "Kingfisher \"Dry\"",
          "bar": "",
          "abv": "7.0"
        },
        {
          "category": "cider",
          "status_text": "",
          "notes": "",
          "id": "a01ede10c5f690d100c911d6a59caf560401f006",
          "allergens": {},
          "dispense": "cider tub",
          "style": "",
          "name": "Kingfisher \"Sweet\"",
          "bar": "",
          "abv": "7.0"
        }
      ],
      "id": "4b68e45a767407ba32c8a08340a8ad86e654cfca",
      "name": "Norfolk Cider Co.",
      "year_founded": ""
    },
    {
      "location": "Norfolk",
      "notes": "Norfolk ",
      "products": [
        {
          "category": "cider",
          "status_text": "",
          "notes": "",
          "id": "468254e2f173ae65c2d04c68d3521d21144cfd79",
          "allergens": {},
          "dispense": "cider tub",
          "style": "",
          "name": "Original",
          "bar": "",
          "abv": "8.2"
        },
        {
          "category": "cider",
          "status_text": "",
          "notes": "",
          "id": "c517865528db4e51034995b67c5f34fdbd71fda8",
          "allergens": {},
          "dispense": "cider tub",
          "style": "",
          "name": "Wingman",
          "bar": "",
          "abv": "6.2"
        }
      ],
      "id": "445cd2fd3273962bdf09425109a2d09f7170e837",
      "name": "Norfolk Raider",
      "year_founded": ""
    },
    {
      "location": "Hertfordshire",
      "notes": "Hertfordshire ",
      "products": [
        {
          "category": "cider",
          "status_text": "",
          "notes": "",
          "id": "f525f542572d86a4362ed765ef2559998ba7b87e",
          "allergens": {},
          "dispense": "cider tub",
          "style": "",
          "name": "Jack o Legs",
          "bar": "",
          "abv": "6.0"
        },
        {
          "category": "cider",
          "status_text": "",
          "notes": "",
          "id": "a4c254f85ef727299c7c796cbc6e1c0aea913fef",
          "allergens": {},
          "dispense": "cider tub",
          "style": "",
          "name": "Offer Rex",
          "bar": "",
          "abv": "5.1"
        }
      ],
      "id": "00a84d7c02fa639f91c4cc532370f2d071612576",
      "name": "Offley",
      "year_founded": ""
    },
    {
      "location": "Suffolk",
      "notes": "Suffolk ",
      "products": [
        {
          "category": "cider",
          "status_text": "",
          "notes": "Soft tannins.",
          "id": "fc04df80d97754b7919d20fe002395bc851e0633",
          "allergens": {},
          "dispense": "cider tub",
          "style": "Medium",
          "name": "Scarlet O'Hara",
          "bar": "",
          "abv": "7.0"
        },
        {
          "category": "cider",
          "status_text": "",
          "notes": "",
          "id": "501e03c6e344fe804ab5a9eb4a7c1387d1692cd3",
          "allergens": {},
          "dispense": "cider tub",
          "style": "",
          "name": "Wild Free & Fruity",
          "bar": "",
          "abv": "7.0"
        }
      ],
      "id": "722a7e9c6dcbb04ed1fffe8d658ea03ce68f8e01",
      "name": "Orwell",
      "year_founded": ""
    },
    {
      "location": "Cambridgeshire",
      "notes": "Cambridgeshire ",
      "products": [
        {
          "category": "cider",
          "status_text": "",
          "notes": "",
          "id": "0d5b1b4d6e79e445400ec44c080893366cc38b11",
          "allergens": {},
          "dispense": "cider tub",
          "style": "",
          "name": "Dabinett (SV)",
          "bar": "",
          "abv": "7.0"
        },
        {
          "category": "cider",
          "status_text": "",
          "notes": "",
          "id": "1ab82a429cd726156b82e3183d209b98d96b14c6",
          "allergens": {},
          "dispense": "cider tub",
          "style": "",
          "name": "Happy Medium",
          "bar": "",
          "abv": "7.4"
        },
        {
          "category": "cider",
          "status_text": "",
          "notes": "",
          "id": "3371140c6b563fd244bc25fafcf954fa98dc113f",
          "allergens": {},
          "dispense": "cider tub",
          "style": "Medium sweet",
          "name": "Sweet Spot",
          "bar": "",
          "abv": "7.4"
        },
        {
          "category": "cider",
          "status_text": "",
          "notes": "",
          "id": "cd1b891a9b6f782bd774009cc92ca16695032e2b",
          "allergens": {},
          "dispense": "cider tub",
          "style": "",
          "name": "Trip Hazard",
          "bar": "",
          "abv": "8.2"
        }
      ],
      "id": "bc60205da2555fc0304c24d2a1b8532bba3350e5",
      "name": "Potton Press",
      "year_founded": ""
    },
    {
      "location": "Bedfordshire",
      "notes": "Bedfordshire ",
      "products": [
        {
          "category": "cider",
          "status_text": "",
          "notes": "",
          "id": "07789e3782695fd60a59abc8a016977c445fbf55",
          "allergens": {},
          "dispense": "cider tub",
          "style": "",
          "name": "Bourbon",
          "bar": "",
          "abv": "8.5"
        },
        {
          "category": "cider",
          "status_text": "",
          "notes": "",
          "id": "fd3d380f2d6ff1895cf74c2ed6ab44dc402d259f",
          "allergens": {},
          "dispense": "cider tub",
          "style": "",
          "name": "Original",
          "bar": "",
          "abv": "5.0"
        },
        {
          "category": "cider",
          "status_text": "",
          "notes": "",
          "id": "1cf47b6e077167d3e6466ce8cd864a64709c62bc",
          "allergens": {},
          "dispense": "cider tub",
          "style": "",
          "name": "Straight Outta the Orchard",
          "bar": "",
          "abv": "7.5"
        },
        {
          "category": "cider",
          "status_text": "",
          "notes": "",
          "id": "52bf08c3839210059151597a4b7c6a3446bbf8ec",
          "allergens": {},
          "dispense": "cider tub",
          "style": "",
          "name": "Traditional (oak matured)",
          "bar": "",
          "abv": "5.8"
        }
      ],
      "id": "3d2d45d4b3f9c8fcd7d9417d5d99a1b5a894ec42",
      "name": "Saxby's",
      "year_founded": ""
    },
    {
      "location": "East Sussex",
      "notes": "East Sussex ",
      "products": [
        {
          "category": "cider",
          "status_text": "",
          "notes": "",
          "id": "b34e94c719452219cec7cf65fa24652205aa0e3a",
          "allergens": {},
          "dispense": "cider tub",
          "style": "",
          "name": "Cider",
          "bar": "",
          "abv": "5.8"
        }
      ],
      "id": "e90e88c880e48e96024e634381ba1ad4888e72e0",
      "name": "Seacider",
      "year_founded": ""
    },
    {
      "location": "Suffolk",
      "notes": "Suffolk ",
      "products": [
        {
          "category": "cider",
          "status_text": "",
          "notes": "",
          "id": "af88245f827669a1df3ed21048e0c473b352cf81",
          "allergens": {},
          "dispense": "cider tub",
          "style": "",
          "name": "Type 22",
          "bar": "",
          "abv": "7.3"
        }
      ],
      "id": "b05e04908505f530a6b70ca64ca05a42ddb1d208",
      "name": "Sicklesmere",
      "year_founded": ""
    },
    {
      "location": "Cambridgeshire",
      "notes": "Cambridgeshire ",
      "products": [
        {
          "category": "cider",
          "status_text": "",
          "notes": "",
          "id": "6fa87a8ed3b25d1a3e5f8685785636417637fcfd",
          "allergens": {},
          "dispense": "cider tub",
          "style": "",
          "name": "Annie Elizabeth (SV) 2018",
          "bar": "",
          "abv": "5.9"
        },
        {
          "category": "cider",
          "status_text": "",
          "notes": "",
          "id": "6d81d6aa42fcac5aafc9969dcf73b144a2a1cfcd",
          "allergens": {},
          "dispense": "cider tub",
          "style": "Medium sweet",
          "name": "COX!!! (SV)",
          "bar": "",
          "abv": "7.3"
        },
        {
          "category": "cider",
          "status_text": "",
          "notes": "",
          "id": "33e16762f10d5fbbf44a266f65d72713c7c7075f",
          "allergens": {},
          "dispense": "cider tub",
          "style": "",
          "name": "Dabinett (SV) ",
          "bar": "",
          "abv": "6.3"
        },
        {
          "category": "cider",
          "status_text": "",
          "notes": "",
          "id": "6df9987ed698bdb44837c3a4dfd1890b936bd000",
          "allergens": {
            "sulphites": true
          },
          "dispense": "cider tub",
          "style": "Medium",
          "name": "East Meets West",
          "bar": "",
          "abv": "6.4"
        },
        {
          "category": "cider",
          "status_text": "",
          "notes": "",
          "id": "c8d91de0ef6f3a189e5564fd1a864b75a80c9ff9",
          "allergens": {},
          "dispense": "cider tub",
          "style": "",
          "name": "Gala (SV) 2018",
          "bar": "",
          "abv": "6.5"
        },
        {
          "category": "cider",
          "status_text": "",
          "notes": "",
          "id": "6ba888cf74ed5fde8e002d79b801d43da5a4c6c4",
          "allergens": {},
          "dispense": "cider tub",
          "style": "",
          "name": "NOMIS (SV Russet)",
          "bar": "",
          "abv": "8.4"
        },
        {
          "category": "cider",
          "status_text": "",
          "notes": "",
          "id": "556342ee926198543f94cd49e9e187768b4f4703",
          "allergens": {},
          "dispense": "cider tub",
          "style": "",
          "name": "Nehou (SV) 2020",
          "bar": "",
          "abv": "6.4"
        },
        {
          "category": "cider",
          "status_text": "",
          "notes": "Blend of Dabinett and Stoke Red",
          "id": "9d76063cf47de8faf2b68695b7bdb825cee22a32",
          "allergens": {},
          "dispense": "cider tub",
          "style": "Dry",
          "name": "Shelford",
          "bar": "",
          "abv": "6.2"
        },
        {
          "category": "cider",
          "status_text": "",
          "notes": "",
          "id": "94f789b0302c038fdfafc3cb6180175a117992ad",
          "allergens": {},
          "dispense": "cider tub",
          "style": "Medium sweet",
          "name": "Short Stirling",
          "bar": "",
          "abv": "4.5"
        },
        {
          "category": "cider",
          "status_text": "",
          "notes": "",
          "id": "9cb2af732b8583784b57ddc6118e211754beb13a",
          "allergens": {},
          "dispense": "cider tub",
          "style": "Sweet",
          "name": "Sweet 'P'",
          "bar": "",
          "abv": "5.6"
        },
        {
          "category": "cider",
          "status_text": "",
          "notes": "",
          "id": "e3ba63df7985c6e9ab0d157ee0271183f89c02a7",
          "allergens": {},
          "dispense": "cider tub",
          "style": "",
          "name": "Sweet Little Nomis (SV Russet)",
          "bar": "",
          "abv": "8.0"
        },
        {
          "category": "cider",
          "status_text": "",
          "notes": "",
          "id": "cc8d382c6d566496d67b7cca0ae77cbdb6e57e98",
          "allergens": {},
          "dispense": "cider tub",
          "style": "",
          "name": "Vice Versa",
          "bar": "",
          "abv": "6.4"
        }
      ],
      "id": "a9e76f7f478c7be32c80f3bb0b7cc06e002d25bb",
      "name": "Simon's Cider",
      "year_founded": ""
    },
    {
      "location": "Cambridgeshire",
      "notes": "Cambridgeshire ",
      "products": [
        {
          "category": "cider",
          "status_text": "",
          "notes": "",
          "id": "b0e1dbd58449e7f6f1964a0f8c45967204b78980",
          "allergens": {},
          "dispense": "cider tub",
          "style": "",
          "name": "Cider",
          "bar": "",
          "abv": "7.0"
        }
      ],
      "id": "2f6ff2c23245604493df6d937f3627842577eefa",
      "name": "Smorgasbord",
      "year_founded": ""
    },
    {
      "location": "Herefordshire",
      "notes": "Herefordshire ",
      "products": [
        {
          "category": "cider",
          "status_text": "",
          "notes": "Rich bronze cider that is smooth as it is tasty. ",
          "id": "f60b874c096c8fbc840cf50d515b68a420e6a61f",
          "allergens": {},
          "dispense": "cider tub",
          "style": "Dry",
          "name": "Pig Squeal",
          "bar": "",
          "abv": "7.0"
        }
      ],
      "id": "685df181be80ff8d2018d3ff7c61f12c471005d2",
      "name": "Snailsbank",
      "year_founded": ""
    },
    {
      "location": "Cambridgeshire",
      "notes": "Cambridgeshire ",
      "products": [
        {
          "category": "cider",
          "status_text": "",
          "notes": "",
          "id": "021956f0959e5b9390533a262d9e0ed6ef33ffd4",
          "allergens": {},
          "dispense": "cider tub",
          "style": "",
          "name": "Dirty Habit",
          "bar": "",
          "abv": "4.0"
        },
        {
          "category": "cider",
          "status_text": "",
          "notes": "",
          "id": "9a50c8a873a65b2b15d3b8d52b9dd9de0559916a",
          "allergens": {},
          "dispense": "cider tub",
          "style": "Medium sweet",
          "name": "Monk and Disorderly",
          "bar": "",
          "abv": "6.1"
        },
        {
          "category": "cider",
          "status_text": "",
          "notes": "",
          "id": "37c5b1d56c31e51b874aef68188dc362e69b3898",
          "allergens": {},
          "dispense": "cider tub",
          "style": "Sweet",
          "name": "Virgin on the Ridiculous",
          "bar": "",
          "abv": "6.1"
        }
      ],
      "id": "cdd30858be416853ee25cea930d52dfe31401311",
      "name": "Spinney Abbey",
      "year_founded": ""
    },
    {
      "location": "Somerset",
      "notes": "Somerset ",
      "products": [
        {
          "category": "cider",
          "status_text": "",
          "notes": "",
          "id": "233a4dffb8e98c3fac0de81b205f55f5408457ee",
          "allergens": {},
          "dispense": "cider tub",
          "style": "",
          "name": "First Press",
          "bar": "",
          "abv": "4.0"
        }
      ],
      "id": "074fe681c9742d991dc00dc287aba5094ff8c678",
      "name": "Taunton Cider",
      "year_founded": ""
    },
    {
      "location": "Normandy, France",
      "notes": "Normandy, France ",
      "products": [
        {
          "category": "cider",
          "status_text": "",
          "notes": "",
          "id": "88dd3ab29c71618c0b6c1d626e5f98c4b781ce26",
          "allergens": {},
          "dispense": "cider tub",
          "style": "",
          "name": "Normandy",
          "bar": "",
          "abv": "7.0"
        }
      ],
      "id": "46b97e6934ff6cda7bf3475ae9287ca1602723a8",
      "name": "Templar's Choice",
      "year_founded": ""
    },
    {
      "location": "Cambridgeshire",
      "notes": "Cambridgeshire ",
      "products": [
        {
          "category": "cider",
          "status_text": "",
          "notes": "",
          "id": "ad90bdfe2a7005b5e2da38a7ea3c2f39056b0313",
          "allergens": {},
          "dispense": "cider tub",
          "style": "",
          "name": "Cider",
          "bar": "",
          "abv": "7.5"
        }
      ],
      "id": "004be89dd9e070ecb080b9b759e5be29ec24881b",
      "name": "That's Malicious",
      "year_founded": ""
    },
    {
      "location": "Norfolk",
      "notes": "Norfolk ",
      "products": [
        {
          "category": "cider",
          "status_text": "",
          "notes": "",
          "id": "9c1721a5581974cfdc54beeae7de4186c8865cb9",
          "allergens": {},
          "dispense": "cider tub",
          "style": "",
          "name": "Dry",
          "bar": "",
          "abv": "5.9"
        },
        {
          "category": "cider",
          "status_text": "",
          "notes": "",
          "id": "6355f0adbbb0d36bf13c89404ce0ffdfc6c0e38a",
          "allergens": {},
          "dispense": "cider tub",
          "style": "",
          "name": "Summer Sweet",
          "bar": "",
          "abv": "4.5"
        }
      ],
      "id": "b609afd886ee8710228d193433a2393491aee9b1",
      "name": "Village Green (Norfolk)",
      "year_founded": ""
    },
    {
      "location": "Cambridgeshire",
      "notes": "Cambridgeshire ",
      "products": [
        {
          "category": "cider",
          "status_text": "",
          "notes": "",
          "id": "51ccd205af04259d55425ebf7a7e1e1663123632",
          "allergens": {},
          "dispense": "cider tub",
          "style": "",
          "name": "Farmhouse",
          "bar": "",
          "abv": "5.0"
        },
        {
          "category": "cider",
          "status_text": "",
          "notes": "",
          "id": "a4ec19f8cc131ac1c2573e86e6d2f0c3652c7172",
          "allergens": {},
          "dispense": "cider tub",
          "style": "",
          "name": "Oak Aged (whiskey cask)",
          "bar": "",
          "abv": "6.0"
        }
      ],
      "id": "6077ad2b372d5a152de8191d73e3e4480c620035",
      "name": "Watergull Orchards",
      "year_founded": ""
    },
    {
      "location": "Norfolk",
      "notes": "Norfolk ",
      "products": [
        {
          "category": "cider",
          "status_text": "",
          "notes": "",
          "id": "71f3da6cd431f5d73b099cb1dd910f0da297835d",
          "allergens": {},
          "dispense": "cider tub",
          "style": "",
          "name": "Dry",
          "bar": "",
          "abv": "6.8"
        }
      ],
      "id": "3977dced04b7d0c7bc81b01a3f4124e14c683b8e",
      "name": "Whin Hill ",
      "year_founded": ""
    },
    {
      "location": "Essex",
      "notes": "Essex ",
      "products": [
        {
          "category": "cider",
          "status_text": "",
          "notes": "",
          "id": "6eb991425cff23c04907c6fa235f7d90ae024603",
          "allergens": {},
          "dispense": "cider tub",
          "style": "",
          "name": "2020 Railway",
          "bar": "",
          "abv": "6.0"
        },
        {
          "category": "cider",
          "status_text": "",
          "notes": "",
          "id": "365e5fa367e9dd4d40c323ccbf06488ffe8521d8",
          "allergens": {},
          "dispense": "cider tub",
          "style": "",
          "name": "The Wild Thing",
          "bar": "",
          "abv": "6.0"
        }
      ],
      "id": "a523c283b9ba4a17676df4b54bad065a94690728",
      "name": "Wrigger's",
      "year_founded": ""
    }
  ],
  "timestamp": "Sun May 21 2023 08:34:41 BST"
}
